bdpyconsts/__init__.py
bdpyconsts/bdpyconsts.py
bdpyconsts-1.1.2.dist-info/METADATA
bdpyconsts-1.1.2.dist-info/WHEEL
bdpyconsts-1.1.2.dist-info/top_level.txt
bdpyconsts-1.1.2.dist-info/RECORD
